pachy
