Metadata-Version: 1.0
Name: pachy
Version: 0.1.1
Summary: Simple incremental backups with rsync and xdelta3
Home-page: http://github.com/bwesterb/pachy/
Author: Bas Westerbaan
Author-email: bas@westerbaan.name
License: UNKNOWN
Platform: UNKNOWN
Classifier: Topic :: System :: Archiving :: Backup
Classifier: License :: OSI Approved :: GNU General Public License (GPL)
Classifier: Development Status :: 4 - Beta
